GeekTools/__init__.py
GeekTools/image_processiong.py
GeekTools-0.0.3.dist-info/LICENSE
GeekTools-0.0.3.dist-info/METADATA
GeekTools-0.0.3.dist-info/WHEEL
GeekTools-0.0.3.dist-info/top_level.txt
GeekTools-0.0.3.dist-info/RECORD
