Metadata-Version: 2.1
Name: GeekTools
Version: 0.0.3
Summary: A toolsbox for AI researcher or engineer.
Home-page: https://github.com/theEeee9/GeekTools
Author: theEeee9
Author-email: 944270057@qq.com
License: UNKNOWN
Platform: UNKNOWN
Classifier: Programming Language :: Python :: 3
Classifier: License :: OSI Approved :: MIT License
Classifier: Operating System :: OS Independent
Requires-Python: >=3.6
